foxha/__init__.py
foxha/connection.py
foxha/crypt.py
foxha/errors.py
foxha/formatter.py
foxha/fox.py
foxha/group.py
foxha/inner_logic.py
foxha/node.py
foxha/node_utils.py
foxha/print_format.py
foxha/query.py
foxha/utils.py
tests/__init__.py
tests/conftest.py
tests/test_crashes.py
tests/test_crud_environment.py
tests/test_failover.py
tests/test_formatter.py
tests/test_fox.py
tests/test_group.py
tests/test_helpers.py
tests/test_inner_logic.py
tests/test_node_logical.py
tests/test_node_physical.py
tests/test_set.py
tests/test_switch.py
tests/test_utils.py
tests/utils_tests/__init__.py
tests/utils_tests/conftest.py
tests/utils_tests/test_connection.py
tests/utils_tests/test_parse_config_file.py
tests/utils_tests/test_parse_key_file.py
foxha-1.0.2.dist-info/LICENSE
foxha-1.0.2.dist-info/METADATA
foxha-1.0.2.dist-info/WHEEL
foxha-1.0.2.dist-info/entry_points.txt
foxha-1.0.2.dist-info/top_level.txt
foxha-1.0.2.dist-info/RECORD
