Metadata-Version: 2.1
Name: foxha
Version: 1.0.2
Summary: A MySQL High Availability tool to replace flipper
Home-page: https://github.com/globocom/foxha/
Author: Rafael Dantas Silva
Author-email: rafael.dantas@corp.globo.com
License: GPL
Keywords: tool mysql
Platform: UNKNOWN
Requires-Dist: enum34 (==1.1.9)
Requires-Dist: six (==1.9.0)
Requires-Dist: pyasn1 (==0.4.8)
Requires-Dist: pycparser (==2.14)
Requires-Dist: cffi (==1.14.5)
Requires-Dist: cryptography (==3.2)
Requires-Dist: mysqlclient (==1.3.12)
Requires-Dist: PTable (==0.9.2)
Requires-Dist: colored (==1.4.2)
Requires-Dist: PyYAML (==6.0)
Requires-Dist: twine (==3.7.0)
Requires-Dist: wheel (==0.37.)
Provides-Extra: dev
Provides-Extra: test
